{
  "match": {
    "match_id": "74061107",
    "name": "MFT7K2021 QF: (MillaMaxwelle) vs (CharlisMadCut)",
    "start_time": "2021-01-23 18:08:11",
    "end_time": "2021-01-23 19:10:28"
  },
  "games": [
    {
      "game_id": "386517613",
      "start_time": "2021-01-23 18:16:01",
      "end_time": "2021-01-23 18:19:44",
      "beatmap_id": "1538402",
      "play_mode": "0",
      "match_type": "0",
      "scoring_type": "3",
      "team_type": "0",
      "mods": "0",
      "scores": [
        {
          "slot": "0",
          "team": "0",
          "user_id": "6264519",
          "score": "702304",
          "maxcombo": "788",
          "rank": "0",
          "count50": "63",
          "count100": "120",
          "count300": "2690",
          "countmiss": "282",
          "countgeki": "4122",
          "countkatu": "515",
          "perfect": "0",
          "pass": "1",
          "enabled_mods": null
        },
        {
          "slot": "1",
          "team": "0",
          "user_id": "2863607",
          "score": "823240",
          "maxcombo": "1282",
          "rank": "0",
          "count50": "13",
          "count100": "65",
          "count300": "2676",
          "countmiss": "118",
          "countgeki": "4558",
          "countkatu": "362",
          "perfect": "0",
          "pass": "1",
          "enabled_mods": null
        }
      ]
    },
    {
      "game_id": "386519448",
      "start_time": "2021-01-23 18:21:32",
      "end_time": "2021-01-23 18:23:43",
      "beatmap_id": "2675962",
      "play_mode": "3",
      "match_type": "0",
      "scoring_type": "3",
      "team_type": "0",
      "mods": "0",
      "scores": [
        {
          "slot": "0",
          "team": "0",
          "user_id": "6264519",
          "score": "942306",
          "maxcombo": "1174",
          "rank": "0",
          "count50": "5",
          "count100": "3",
          "count300": "471",
          "countmiss": "8",
          "countgeki": "1929",
          "countkatu": "23",
          "perfect": "0",
          "pass": "1",
          "enabled_mods": null
        },
        {
          "slot": "1",
          "team": "0",
          "user_id": "2863607",
          "score": "891488",
          "maxcombo": "1066",
          "rank": "0",
          "count50": "3",
          "count100": "6",
          "count300": "777",
          "countmiss": "10",
          "countgeki": "1538",
          "countkatu": "105",
          "perfect": "0",
          "pass": "1",
          "enabled_mods": null
        }
      ]
    },
    {
      "game_id": "386522138",
      "start_time": "2021-01-23 18:29:53",
      "end_time": "2021-01-23 18:32:20",
      "beatmap_id": "1569469",
      "play_mode": "3",
      "match_type": "0",
      "scoring_type": "3",
      "team_type": "0",
      "mods": "0",
      "scores": [
        {
          "slot": "0",
          "team": "0",
          "user_id": "6264519",
          "score": "979802",
          "maxcombo": "1658",
          "rank": "0",
          "count50": "0",
          "count100": "2",
          "count300": "292",
          "countmiss": "0",
          "countgeki": "1352",
          "countkatu": "12",
          "perfect": "0",
          "pass": "1",
          "enabled_mods": "0"
        },
        {
          "slot": "1",
          "team": "0",
          "user_id": "2863607",
          "score": "935862",
          "maxcombo": "714",
          "rank": "0",
          "count50": "0",
          "count100": "2",
          "count300": "415",
          "countmiss": "3",
          "countgeki": "1209",
          "countkatu": "29",
          "perfect": "0",
          "pass": "1",
          "enabled_mods": "0"
        }
      ]
    },
    {
      "game_id": "386523249",
      "start_time": "2021-01-23 18:33:18",
      "end_time": "2021-01-23 18:36:11",
      "beatmap_id": "1515408",
      "play_mode": "3",
      "match_type": "0",
      "scoring_type": "3",
      "team_type": "0",
      "mods": "0",
      "scores": [
        {
          "slot": "0",
          "team": "0",
          "user_id": "6264519",
          "score": "880816",
          "maxcombo": "632",
          "rank": "0",
          "count50": "4",
          "count100": "10",
          "count300": "563",
          "countmiss": "4",
          "countgeki": "981",
          "countkatu": "62",
          "perfect": "0",
          "pass": "1",
          "enabled_mods": "0"
        },
        {
          "slot": "1",
          "team": "0",
          "user_id": "2863607",
          "score": "931940",
          "maxcombo": "1077",
          "rank": "0",
          "count50": "0",
          "count100": "8",
          "count300": "569",
          "countmiss": "1",
          "countgeki": "1004",
          "countkatu": "42",
          "perfect": "0",
          "pass": "1",
          "enabled_mods": "0"
        }
      ]
    },
    {
      "game_id": "386524494",
      "start_time": "2021-01-23 18:37:10",
      "end_time": "2021-01-23 18:39:28",
      "beatmap_id": "2796515",
      "play_mode": "3",
      "match_type": "0",
      "scoring_type": "3",
      "team_type": "0",
      "mods": "0",
      "scores": [
        {
          "slot": "0",
          "team": "0",
          "user_id": "6264519",
          "score": "886455",
          "maxcombo": "538",
          "rank": "0",
          "count50": "3",
          "count100": "14",
          "count300": "372",
          "countmiss": "15",
          "countgeki": "1539",
          "countkatu": "34",
          "perfect": "0",
          "pass": "1",
          "enabled_mods": "0"
        },
        {
          "slot": "1",
          "team": "0",
          "user_id": "2863607",
          "score": "935292",
          "maxcombo": "1602",
          "rank": "0",
          "count50": "2",
          "count100": "5",
          "count300": "511",
          "countmiss": "6",
          "countgeki": "1422",
          "countkatu": "31",
          "perfect": "0",
          "pass": "1",
          "enabled_mods": "1073741824"
        }
      ]
    },
    {
      "game_id": "386525857",
      "start_time": "2021-01-23 18:41:28",
      "end_time": "2021-01-23 18:45:56",
      "beatmap_id": "1860567",
      "play_mode": "3",
      "match_type": "0",
      "scoring_type": "3",
      "team_type": "0",
      "mods": "0",
      "scores": [
        {
          "slot": "0",
          "team": "0",
          "user_id": "6264519",
          "score": "938285",
          "maxcombo": "2642",
          "rank": "0",
          "count50": "3",
          "count100": "19",
          "count300": "1495",
          "countmiss": "7",
          "countgeki": "4148",
          "countkatu": "118",
          "perfect": "0",
          "pass": "1",
          "enabled_mods": "0"
        },
        {
          "slot": "1",
          "team": "0",
          "user_id": "2863607",
          "score": "931969",
          "maxcombo": "3810",
          "rank": "0",
          "count50": "4",
          "count100": "10",
          "count300": "1928",
          "countmiss": "6",
          "countgeki": "3656",
          "countkatu": "186",
          "perfect": "0",
          "pass": "1",
          "enabled_mods": "0"
        }
      ]
    },
    {
      "game_id": "386527651",
      "start_time": "2021-01-23 18:47:00",
      "end_time": "2021-01-23 18:48:53",
      "beatmap_id": "2068682",
      "play_mode": "3",
      "match_type": "0",
      "scoring_type": "3",
      "team_type": "0",
      "mods": "0",
      "scores": [
        {
          "slot": "0",
          "team": "0",
          "user_id": "6264519",
          "score": "975989",
          "maxcombo": "1135",
          "rank": "0",
          "count50": "1",
          "count100": "0",
          "count300": "195",
          "countmiss": "1",
          "countgeki": "1289",
          "countkatu": "5",
          "perfect": "0",
          "pass": "1",
          "enabled_mods": "0"
        },
        {
          "slot": "1",
          "team": "0",
          "user_id": "2863607",
          "score": "936979",
          "maxcombo": "961",
          "rank": "0",
          "count50": "1",
          "count100": "4",
          "count300": "350",
          "countmiss": "2",
          "countgeki": "1105",
          "countkatu": "29",
          "perfect": "0",
          "pass": "1",
          "enabled_mods": "0"
        }
      ]
    },
    {
      "game_id": "386528988",
      "start_time": "2021-01-23 18:51:02",
      "end_time": "2021-01-23 18:52:55",
      "beatmap_id": "1374654",
      "play_mode": "3",
      "match_type": "0",
      "scoring_type": "3",
      "team_type": "0",
      "mods": "0",
      "scores": [
        {
          "slot": "0",
          "team": "0",
          "user_id": "6264519",
          "score": "970722",
          "maxcombo": "773",
          "rank": "0",
          "count50": "0",
          "count100": "1",
          "count300": "172",
          "countmiss": "1",
          "countgeki": "1106",
          "countkatu": "8",
          "perfect": "0",
          "pass": "1",
          "enabled_mods": "0"
        },
        {
          "slot": "1",
          "team": "0",
          "user_id": "2863607",
          "score": "989434",
          "maxcombo": "1288",
          "rank": "0",
          "count50": "0",
          "count100": "0",
          "count300": "127",
          "countmiss": "0",
          "countgeki": "1155",
          "countkatu": "6",
          "perfect": "0",
          "pass": "1",
          "enabled_mods": "0"
        }
      ]
    },
    {
      "game_id": "386530945",
      "start_time": "2021-01-23 18:56:57",
      "end_time": "2021-01-23 18:58:44",
      "beatmap_id": "1323979",
      "play_mode": "3",
      "match_type": "0",
      "scoring_type": "3",
      "team_type": "0",
      "mods": "0",
      "scores": [
        {
          "slot": "0",
          "team": "0",
          "user_id": "6264519",
          "score": "990872",
          "maxcombo": "1160",
          "rank": "0",
          "count50": "0",
          "count100": "0",
          "count300": "203",
          "countmiss": "0",
          "countgeki": "957",
          "countkatu": "0",
          "perfect": "0",
          "pass": "1",
          "enabled_mods": "16"
        },
        {
          "slot": "1",
          "team": "0",
          "user_id": "2863607",
          "score": "976479",
          "maxcombo": "1160",
          "rank": "0",
          "count50": "0",
          "count100": "0",
          "count300": "261",
          "countmiss": "0",
          "countgeki": "887",
          "countkatu": "12",
          "perfect": "0",
          "pass": "1",
          "enabled_mods": "16"
        }
      ]
    },
    {
      "game_id": "386531976",
      "start_time": "2021-01-23 19:00:08",
      "end_time": "2021-01-23 19:02:13",
      "beatmap_id": "1546340",
      "play_mode": "3",
      "match_type": "0",
      "scoring_type": "3",
      "team_type": "0",
      "mods": "0",
      "scores": [
        {
          "slot": "0",
          "team": "0",
          "user_id": "6264519",
          "score": "569950",
          "maxcombo": "302",
          "rank": "0",
          "count50": "11",
          "count100": "38",
          "count300": "480",
          "countmiss": "21",
          "countgeki": "361",
          "countkatu": "310",
          "perfect": "0",
          "pass": "1",
          "enabled_mods": "0"
        },
        {
          "slot": "1",
          "team": "0",
          "user_id": "2863607",
          "score": "603966",
          "maxcombo": "364",
          "rank": "0",
          "count50": "15",
          "count100": "66",
          "count300": "447",
          "countmiss": "18",
          "countgeki": "473",
          "countkatu": "202",
          "perfect": "0",
          "pass": "1",
          "enabled_mods": "0"
        }
      ]
    },
    {
      "game_id": "386533163",
      "start_time": "2021-01-23 19:03:36",
      "end_time": "2021-01-23 19:07:53",
      "beatmap_id": "1876836",
      "play_mode": "3",
      "match_type": "0",
      "scoring_type": "3",
      "team_type": "0",
      "mods": "0",
      "scores": [
        {
          "slot": "0",
          "team": "0",
          "user_id": "6264519",
          "score": "908476",
          "maxcombo": "777",
          "rank": "0",
          "count50": "4",
          "count100": "15",
          "count300": "923",
          "countmiss": "17",
          "countgeki": "2958",
          "countkatu": "88",
          "perfect": "0",
          "pass": "1",
          "enabled_mods": "0"
        },
        {
          "slot": "1",
          "team": "0",
          "user_id": "2863607",
          "score": "887873",
          "maxcombo": "1152",
          "rank": "0",
          "count50": "5",
          "count100": "13",
          "count300": "1347",
          "countmiss": "11",
          "countgeki": "2441",
          "countkatu": "188",
          "perfect": "0",
          "pass": "1",
          "enabled_mods": "0"
        }
      ]
    }
  ]
}
