{
  "match": {
    "match_id": "78675148",
    "name": "SOFT5: (mashu) vs (Tupidix)",
    "start_time": "2021-03-21 19:26:52",
    "end_time": "2021-03-21 20:01:46"
  },
  "games": [
    {
      "game_id": "407204756",
      "start_time": "2021-03-21 19:32:46",
      "end_time": "2021-03-21 19:36:02",
      "beatmap_id": "2557832",
      "play_mode": "3",
      "match_type": "0",
      "scoring_type": "3",
      "team_type": "0",
      "mods": "0",
      "scores": [
        {
          "slot": "0",
          "team": "0",
          "user_id": "12028216",
          "score": "992403",
          "maxcombo": "3424",
          "rank": "0",
          "count50": "0",
          "count100": "0",
          "count300": "409",
          "countmiss": "0",
          "countgeki": "3011",
          "countkatu": "4",
          "perfect": "0",
          "pass": "1",
          "enabled_mods": null
        },
        {
          "slot": "1",
          "team": "0",
          "user_id": "8655604",
          "score": "952509",
          "maxcombo": "2345",
          "rank": "0",
          "count50": "2",
          "count100": "3",
          "count300": "756",
          "countmiss": "4",
          "countgeki": "2593",
          "countkatu": "66",
          "perfect": "0",
          "pass": "1",
          "enabled_mods": null
        }
      ]
    },
    {
      "game_id": "407206417",
      "start_time": "2021-03-21 19:37:48",
      "end_time": "2021-03-21 19:39:54",
      "beatmap_id": "1655420",
      "play_mode": "3",
      "match_type": "0",
      "scoring_type": "3",
      "team_type": "0",
      "mods": "0",
      "scores": [
        {
          "slot": "0",
          "team": "0",
          "user_id": "12028216",
          "score": "973404",
          "maxcombo": "1277",
          "rank": "0",
          "count50": "0",
          "count100": "0",
          "count300": "297",
          "countmiss": "1",
          "countgeki": "1686",
          "countkatu": "18",
          "perfect": "0",
          "pass": "1",
          "enabled_mods": null
        },
        {
          "slot": "1",
          "team": "0",
          "user_id": "8655604",
          "score": "949177",
          "maxcombo": "863",
          "rank": "0",
          "count50": "0",
          "count100": "0",
          "count300": "305",
          "countmiss": "5",
          "countgeki": "1670",
          "countkatu": "22",
          "perfect": "0",
          "pass": "1",
          "enabled_mods": null
        }
      ]
    },
    {
      "game_id": "407208393",
      "start_time": "2021-03-21 19:43:15",
      "end_time": "2021-03-21 19:45:16",
      "beatmap_id": "2594424",
      "play_mode": "3",
      "match_type": "0",
      "scoring_type": "3",
      "team_type": "0",
      "mods": "0",
      "scores": [
        {
          "slot": "0",
          "team": "0",
          "user_id": "12028216",
          "score": "995772",
          "maxcombo": "1782",
          "rank": "0",
          "count50": "0",
          "count100": "0",
          "count300": "144",
          "countmiss": "0",
          "countgeki": "1638",
          "countkatu": "0",
          "perfect": "0",
          "pass": "1",
          "enabled_mods": "1073741824"
        },
        {
          "slot": "1",
          "team": "0",
          "user_id": "8655604",
          "score": "993170",
          "maxcombo": "1782",
          "rank": "0",
          "count50": "0",
          "count100": "0",
          "count300": "233",
          "countmiss": "0",
          "countgeki": "1549",
          "countkatu": "0",
          "perfect": "0",
          "pass": "1",
          "enabled_mods": "0"
        }
      ]
    },
    {
      "game_id": "407209480",
      "start_time": "2021-03-21 19:46:26",
      "end_time": "2021-03-21 19:48:38",
      "beatmap_id": "2576356",
      "play_mode": "3",
      "match_type": "0",
      "scoring_type": "3",
      "team_type": "0",
      "mods": "0",
      "scores": [
        {
          "slot": "0",
          "team": "0",
          "user_id": "12028216",
          "score": "993909",
          "maxcombo": "2056",
          "rank": "0",
          "count50": "0",
          "count100": "0",
          "count300": "195",
          "countmiss": "0",
          "countgeki": "1859",
          "countkatu": "2",
          "perfect": "0",
          "pass": "1",
          "enabled_mods": "0"
        },
        {
          "slot": "1",
          "team": "0",
          "user_id": "8655604",
          "score": "980854",
          "maxcombo": "2056",
          "rank": "0",
          "count50": "0",
          "count100": "1",
          "count300": "403",
          "countmiss": "0",
          "countgeki": "1638",
          "countkatu": "14",
          "perfect": "0",
          "pass": "1",
          "enabled_mods": "0"
        }
      ]
    },
    {
      "game_id": "407210828",
      "start_time": "2021-03-21 19:50:06",
      "end_time": "2021-03-21 19:52:35",
      "beatmap_id": "2658672",
      "play_mode": "3",
      "match_type": "0",
      "scoring_type": "3",
      "team_type": "0",
      "mods": "0",
      "scores": [
        {
          "slot": "0",
          "team": "0",
          "user_id": "12028216",
          "score": "995981",
          "maxcombo": "1940",
          "rank": "0",
          "count50": "0",
          "count100": "0",
          "count300": "149",
          "countmiss": "0",
          "countgeki": "1791",
          "countkatu": "0",
          "perfect": "0",
          "pass": "1",
          "enabled_mods": "1073741824"
        },
        {
          "slot": "1",
          "team": "0",
          "user_id": "8655604",
          "score": "993832",
          "maxcombo": "1940",
          "rank": "0",
          "count50": "0",
          "count100": "0",
          "count300": "229",
          "countmiss": "0",
          "countgeki": "1711",
          "countkatu": "0",
          "perfect": "0",
          "pass": "1",
          "enabled_mods": "0"
        }
      ]
    },
    {
      "game_id": "407212219",
      "start_time": "2021-03-21 19:53:52",
      "end_time": "2021-03-21 19:56:04",
      "beatmap_id": "2893113",
      "play_mode": "3",
      "match_type": "0",
      "scoring_type": "3",
      "team_type": "0",
      "mods": "0",
      "scores": [
        {
          "slot": "0",
          "team": "0",
          "user_id": "12028216",
          "score": "994315",
          "maxcombo": "2265",
          "rank": "0",
          "count50": "0",
          "count100": "0",
          "count300": "224",
          "countmiss": "0",
          "countgeki": "2040",
          "countkatu": "1",
          "perfect": "0",
          "pass": "1",
          "enabled_mods": "0"
        },
        {
          "slot": "1",
          "team": "0",
          "user_id": "8655604",
          "score": "984299",
          "maxcombo": "2265",
          "rank": "0",
          "count50": "0",
          "count100": "0",
          "count300": "439",
          "countmiss": "0",
          "countgeki": "1815",
          "countkatu": "11",
          "perfect": "0",
          "pass": "1",
          "enabled_mods": "0"
        }
      ]
    }
  ]
}
