{
  "avatar_url": "https://a.ppy.sh/14306726?1604042883.jpeg",
  "country_code": "BE",
  "default_group": "default",
  "id": 14306726,
  "is_active": true,
  "is_bot": false,
  "is_deleted": false,
  "is_online": true,
  "is_supporter": false,
  "last_visit": "2021-01-24T22:57:00+00:00",
  "pm_friends_only": false,
  "profile_colour": null,
  "username": "furious_0803",
  "comments_count": 5,
  "cover_url": "https://osu.ppy.sh/images/headers/profile-covers/c6.jpg",
  "discord": null,
  "has_supported": false,
  "interests": null,
  "join_date": "2019-04-19T17:08:25+00:00",
  "kudosu": { "total": 0, "available": 0 },
  "location": null,
  "max_blocks": 25,
  "max_friends": 250,
  "occupation": null,
  "playmode": "mania",
  "playstyle": ["keyboard", "tablet"],
  "post_count": 0,
  "profile_order": [
    "me",
    "recent_activity",
    "top_ranks",
    "medals",
    "historical",
    "beatmaps",
    "kudosu"
  ],
  "skype": null,
  "title": null,
  "title_url": null,
  "twitter": null,
  "website": null,
  "country": { "code": "BE", "name": "Belgium" },
  "cover": {
    "custom_url": null,
    "url": "https://osu.ppy.sh/images/headers/profile-covers/c6.jpg",
    "id": "6"
  },
  "account_history": [],
  "active_tournament_banner": [],
  "badges": [],
  "beatmap_playcounts_count": 4134,
  "favourite_beatmapset_count": 34,
  "follower_count": 63,
  "graveyard_beatmapset_count": 0,
  "groups": [],
  "loved_beatmapset_count": 0,
  "mapping_follower_count": 0,
  "monthly_playcounts": [
    { "start_date": "2019-04-01", "count": 21 },
    { "start_date": "2019-06-01", "count": 228 },
    { "start_date": "2019-07-01", "count": 188 },
    { "start_date": "2019-09-01", "count": 324 },
    { "start_date": "2019-10-01", "count": 1765 },
    { "start_date": "2019-11-01", "count": 2826 },
    { "start_date": "2019-12-01", "count": 1812 },
    { "start_date": "2020-01-01", "count": 286 },
    { "start_date": "2020-02-01", "count": 125 },
    { "start_date": "2020-03-01", "count": 61 },
    { "start_date": "2020-04-01", "count": 294 },
    { "start_date": "2020-05-01", "count": 1417 },
    { "start_date": "2020-06-01", "count": 3344 },
    { "start_date": "2020-07-01", "count": 1681 },
    { "start_date": "2020-08-01", "count": 1482 },
    { "start_date": "2020-09-01", "count": 2350 },
    { "start_date": "2020-10-01", "count": 2251 },
    { "start_date": "2020-11-01", "count": 1363 },
    { "start_date": "2020-12-01", "count": 888 },
    { "start_date": "2021-01-01", "count": 442 }
  ],
  "previous_usernames": [],
  "ranked_and_approved_beatmapset_count": 0,
  "replays_watched_counts": [
    { "start_date": "2019-10-01", "count": 2 },
    { "start_date": "2020-06-01", "count": 1 },
    { "start_date": "2020-08-01", "count": 3 },
    { "start_date": "2020-09-01", "count": 1 },
    { "start_date": "2020-10-01", "count": 1 }
  ],
  "scores_best_count": 100,
  "scores_first_count": 0,
  "scores_recent_count": 0,
  "statistics": {
    "level": { "current": 78, "progress": 87 },
    "pp": 6256.58,
    "pp_rank": 4707,
    "ranked_score": 836363623,
    "hit_accuracy": 95.0996,
    "play_count": 10539,
    "play_time": 733247,
    "total_score": 3240822556,
    "total_hits": 6547590,
    "maximum_combo": 3870,
    "replays_watched_by_others": 7,
    "is_ranked": true,
    "grade_counts": { "ss": 31, "ssh": 1, "s": 625, "sh": 6, "a": 239 },
    "rank": { "global": 4707, "country": 19 },
    "variants": [
      {
        "mode": "mania",
        "variant": "4k",
        "country_rank": 18,
        "global_rank": 3506,
        "pp": 6206.54
      },
      {
        "mode": "mania",
        "variant": "7k",
        "country_rank": 50,
        "global_rank": 12592,
        "pp": 632.679
      }
    ]
  },
  "support_level": 0,
  "unranked_beatmapset_count": 0,
  "user_achievements": [
    { "achieved_at": "2020-11-01T14:31:02+00:00", "achievement_id": 126 },
    { "achieved_at": "2020-10-13T19:52:37+00:00", "achievement_id": 222 },
    { "achieved_at": "2020-10-13T19:52:37+00:00", "achievement_id": 68 },
    { "achieved_at": "2020-10-03T16:38:19+00:00", "achievement_id": 61 },
    { "achieved_at": "2020-09-26T10:14:22+00:00", "achievement_id": 67 },
    { "achieved_at": "2020-08-16T10:39:37+00:00", "achievement_id": 20 },
    { "achieved_at": "2020-08-12T20:06:08+00:00", "achievement_id": 52 },
    { "achieved_at": "2020-08-12T19:38:47+00:00", "achievement_id": 93 },
    { "achieved_at": "2020-07-22T14:12:36+00:00", "achievement_id": 60 },
    { "achieved_at": "2020-07-02T19:56:51+00:00", "achievement_id": 39 },
    { "achieved_at": "2020-06-28T14:14:29+00:00", "achievement_id": 121 },
    { "achieved_at": "2020-06-20T16:45:19+00:00", "achievement_id": 66 },
    { "achieved_at": "2020-06-19T19:22:14+00:00", "achievement_id": 59 },
    { "achieved_at": "2020-06-16T15:28:45+00:00", "achievement_id": 120 },
    { "achieved_at": "2020-06-16T11:12:42+00:00", "achievement_id": 1 },
    { "achieved_at": "2020-06-14T17:58:00+00:00", "achievement_id": 144 },
    { "achieved_at": "2020-06-01T20:02:27+00:00", "achievement_id": 51 },
    { "achieved_at": "2020-05-19T16:22:51+00:00", "achievement_id": 65 },
    { "achieved_at": "2020-05-18T21:58:30+00:00", "achievement_id": 40 },
    { "achieved_at": "2020-05-15T00:15:13+00:00", "achievement_id": 58 },
    { "achieved_at": "2020-04-19T12:54:34+00:00", "achievement_id": 64 },
    { "achieved_at": "2020-03-27T23:43:11+00:00", "achievement_id": 48 },
    { "achieved_at": "2019-12-31T08:00:10+00:00", "achievement_id": 13 },
    { "achieved_at": "2019-12-30T21:57:43+00:00", "achievement_id": 103 },
    { "achieved_at": "2019-12-26T15:12:34+00:00", "achievement_id": 92 },
    { "achieved_at": "2019-12-24T20:18:34+00:00", "achievement_id": 152 },
    { "achieved_at": "2019-12-15T13:15:04+00:00", "achievement_id": 119 },
    { "achieved_at": "2019-12-14T22:14:35+00:00", "achievement_id": 80 },
    { "achieved_at": "2019-11-26T19:02:48+00:00", "achievement_id": 114 },
    { "achieved_at": "2019-11-23T22:40:46+00:00", "achievement_id": 177 },
    { "achieved_at": "2019-11-23T09:50:47+00:00", "achievement_id": 91 },
    { "achieved_at": "2019-11-18T18:31:04+00:00", "achievement_id": 128 },
    { "achieved_at": "2019-11-14T19:12:14+00:00", "achievement_id": 113 },
    { "achieved_at": "2019-11-11T11:58:49+00:00", "achievement_id": 50 },
    { "achieved_at": "2019-10-29T13:03:52+00:00", "achievement_id": 90 },
    { "achieved_at": "2019-10-20T10:52:32+00:00", "achievement_id": 57 },
    { "achieved_at": "2019-10-13T16:15:37+00:00", "achievement_id": 47 },
    { "achieved_at": "2019-10-09T18:02:46+00:00", "achievement_id": 72 },
    { "achieved_at": "2019-10-04T22:17:58+00:00", "achievement_id": 63 },
    { "achieved_at": "2019-10-02T19:00:17+00:00", "achievement_id": 112 },
    { "achieved_at": "2019-10-01T16:17:05+00:00", "achievement_id": 138 },
    { "achieved_at": "2019-09-28T14:07:48+00:00", "achievement_id": 132 },
    { "achieved_at": "2019-09-28T13:18:18+00:00", "achievement_id": 89 },
    { "achieved_at": "2019-09-27T18:36:55+00:00", "achievement_id": 42 },
    { "achieved_at": "2019-09-25T12:13:25+00:00", "achievement_id": 127 },
    { "achieved_at": "2019-09-23T18:40:18+00:00", "achievement_id": 176 },
    { "achieved_at": "2019-07-22T11:09:41+00:00", "achievement_id": 137 },
    { "achieved_at": "2019-07-03T19:33:38+00:00", "achievement_id": 123 },
    { "achieved_at": "2019-07-02T19:10:53+00:00", "achievement_id": 79 },
    { "achieved_at": "2019-07-01T20:19:53+00:00", "achievement_id": 125 },
    { "achieved_at": "2019-07-01T20:00:50+00:00", "achievement_id": 56 },
    { "achieved_at": "2019-06-30T11:44:49+00:00", "achievement_id": 124 },
    { "achieved_at": "2019-06-28T11:07:00+00:00", "achievement_id": 46 },
    { "achieved_at": "2019-06-27T19:48:49+00:00", "achievement_id": 122 },
    { "achieved_at": "2019-06-27T16:47:33+00:00", "achievement_id": 111 },
    { "achieved_at": "2019-06-27T16:47:33+00:00", "achievement_id": 87 },
    { "achieved_at": "2019-06-27T16:39:37+00:00", "achievement_id": 88 },
    { "achieved_at": "2019-06-27T16:39:37+00:00", "achievement_id": 54 },
    { "achieved_at": "2019-04-19T17:49:02+00:00", "achievement_id": 55 }
  ],
  "rankHistory": {
    "mode": "mania",
    "data": [
      4255,
      4261,
      4265,
      4271,
      4276,
      4280,
      4284,
      4289,
      4296,
      4302,
      4304,
      4307,
      4314,
      4316,
      4316,
      4323,
      4328,
      4329,
      4336,
      4339,
      4343,
      4349,
      4358,
      4361,
      4366,
      4370,
      4375,
      4380,
      4389,
      4395,
      4397,
      4410,
      4417,
      4424,
      4429,
      4438,
      4444,
      4447,
      4453,
      4461,
      4467,
      4474,
      4477,
      4483,
      4481,
      4486,
      4492,
      4493,
      4500,
      4508,
      4509,
      4516,
      4523,
      4527,
      4530,
      4535,
      4540,
      4542,
      4546,
      4552,
      4559,
      4562,
      4567,
      4573,
      4581,
      4589,
      4595,
      4599,
      4606,
      4614,
      4619,
      4623,
      4629,
      4630,
      4631,
      4641,
      4647,
      4649,
      4649,
      4653,
      4659,
      4664,
      4672,
      4686,
      4687,
      4692,
      4696,
      4699,
      4706,
      4707
    ]
  },
  "rank_history": {
    "mode": "mania",
    "data": [
      4255,
      4261,
      4265,
      4271,
      4276,
      4280,
      4284,
      4289,
      4296,
      4302,
      4304,
      4307,
      4314,
      4316,
      4316,
      4323,
      4328,
      4329,
      4336,
      4339,
      4343,
      4349,
      4358,
      4361,
      4366,
      4370,
      4375,
      4380,
      4389,
      4395,
      4397,
      4410,
      4417,
      4424,
      4429,
      4438,
      4444,
      4447,
      4453,
      4461,
      4467,
      4474,
      4477,
      4483,
      4481,
      4486,
      4492,
      4493,
      4500,
      4508,
      4509,
      4516,
      4523,
      4527,
      4530,
      4535,
      4540,
      4542,
      4546,
      4552,
      4559,
      4562,
      4567,
      4573,
      4581,
      4589,
      4595,
      4599,
      4606,
      4614,
      4619,
      4623,
      4629,
      4630,
      4631,
      4641,
      4647,
      4649,
      4649,
      4653,
      4659,
      4664,
      4672,
      4686,
      4687,
      4692,
      4696,
      4699,
      4706,
      4707
    ]
  }
}
