{
  "id": "5.qf",
  "name": "Quarterfinals",
  "mapCount": 15,
  "maps": [
    {
      "category": "rice",
      "counts": {
        "bpm": -1,
        "sv": -1,
        "notes": {
          "total": 1728,
          "rice": 1728,
          "ln": 0,
          "single": -1,
          "jump": -1,
          "hand": -1,
          "quad": -1
        }
      },
      "title": "PAPERMOON",
      "artist": "Tommy heavenly6",
      "mapper": "lemonguy",
      "difficulty": "[4K] Skwid's Challenge",
      "beatmapId": "2942945",
      "beatmapSetId": "1429569",
      "hp": 8,
      "od": 8.5,
      "scores": [
        {
          "userId": "5243536",
          "score": 995147,
          "combo": 1728,
          "counts": {
            "50": 0,
            "100": 0,
            "200": 1,
            "300": 138,
            "miss": 0,
            "max": 1589
          }
        },
        {
          "userId": "169992",
          "score": 994524,
          "combo": 1728,
          "counts": {
            "50": 0,
            "100": 0,
            "200": 0,
            "300": 181,
            "miss": 0,
            "max": 1547
          }
        },
        {
          "userId": "5243536",
          "score": 994032,
          "combo": 1728,
          "counts": {
            "50": 0,
            "100": 0,
            "200": 1,
            "300": 175,
            "miss": 0,
            "max": 1552
          }
        },
        {
          "userId": "10242062",
          "score": 993590,
          "combo": 1728,
          "counts": {
            "50": 0,
            "100": 0,
            "200": 0,
            "300": 212,
            "miss": 0,
            "max": 1516
          }
        },
        {
          "userId": "3799946",
          "score": 991294,
          "combo": 1728,
          "counts": {
            "50": 0,
            "100": 0,
            "200": 1,
            "300": 266,
            "miss": 0,
            "max": 1461
          }
        },
        {
          "userId": "11888159",
          "score": 990974,
          "combo": 1728,
          "counts": {
            "50": 0,
            "100": 0,
            "200": 3,
            "300": 232,
            "miss": 0,
            "max": 1493
          }
        },
        {
          "userId": "13347579",
          "score": 988776,
          "combo": 1728,
          "counts": {
            "50": 0,
            "100": 0,
            "200": 4,
            "300": 283,
            "miss": 0,
            "max": 1441
          }
        },
        {
          "userId": "3799946",
          "score": 987969,
          "combo": 1728,
          "counts": {
            "50": 0,
            "100": 0,
            "200": 5,
            "300": 288,
            "miss": 0,
            "max": 1435
          }
        },
        {
          "userId": "11517895",
          "score": 984832,
          "combo": 1728,
          "counts": {
            "50": 0,
            "100": 0,
            "200": 7,
            "300": 348,
            "miss": 0,
            "max": 1373
          }
        },
        {
          "userId": "4980256",
          "score": 983661,
          "combo": 1728,
          "counts": {
            "50": 0,
            "100": 0,
            "200": 8,
            "300": 365,
            "miss": 0,
            "max": 1355
          }
        },
        {
          "userId": "5156656",
          "score": 982089,
          "combo": 1323,
          "counts": {
            "50": 0,
            "100": 0,
            "200": 1,
            "300": 171,
            "miss": 2,
            "max": 1554
          }
        },
        {
          "userId": "15806513",
          "score": 981412,
          "combo": 1371,
          "counts": {
            "50": 0,
            "100": 0,
            "200": 2,
            "300": 245,
            "miss": 1,
            "max": 1480
          }
        },
        {
          "userId": "12028216",
          "score": 977080,
          "combo": 887,
          "counts": {
            "50": 0,
            "100": 0,
            "200": 4,
            "300": 344,
            "miss": 1,
            "max": 1379
          }
        },
        {
          "userId": "5156656",
          "score": 976427,
          "combo": 990,
          "counts": {
            "50": 1,
            "100": 0,
            "200": 0,
            "300": 148,
            "miss": 2,
            "max": 1577
          }
        },
        {
          "userId": "7341471",
          "score": 975175,
          "combo": 1728,
          "counts": {
            "50": 0,
            "100": 0,
            "200": 16,
            "300": 473,
            "miss": 0,
            "max": 1239
          }
        },
        {
          "userId": "13382147",
          "score": 957629,
          "combo": 1032,
          "counts": {
            "50": 0,
            "100": 0,
            "200": 18,
            "300": 367,
            "miss": 2,
            "max": 1341
          }
        }
      ],
      "pickCount": 8
    },
    {
      "category": "rice",
      "counts": {
        "bpm": -1,
        "sv": -1,
        "notes": {
          "total": 2057,
          "rice": 2057,
          "ln": 0,
          "single": -1,
          "jump": -1,
          "hand": -1,
          "quad": -1
        }
      },
      "title": "Nanamori (youth Remix)",
      "artist": "Kotori",
      "mapper": "Shoegazer",
      "difficulty": "[4K] Escapade 1.15x (247bpm)",
      "beatmapId": "2816502",
      "beatmapSetId": "1360301",
      "hp": 8.5,
      "od": 8.5,
      "scores": [],
      "pickCount": 0
    },
    {
      "category": "rice",
      "counts": {
        "bpm": -1,
        "sv": -1,
        "notes": {
          "total": 4833,
          "rice": 4826,
          "ln": 7,
          "single": -1,
          "jump": -1,
          "hand": -1,
          "quad": -1
        }
      },
      "title": "BLUE NOAH 2006",
      "artist": "DJ Sharpnel",
      "mapper": "Wh1teh",
      "difficulty": "[4K] 1.2x",
      "beatmapId": "2874328",
      "beatmapSetId": "1392117",
      "hp": 8.5,
      "od": 8.5,
      "scores": [
        {
          "userId": "10083439",
          "score": 998506,
          "combo": 4840,
          "counts": {
            "50": 0,
            "100": 0,
            "200": 0,
            "300": 138,
            "miss": 0,
            "max": 4702
          }
        },
        {
          "userId": "10242062",
          "score": 997969,
          "combo": 4840,
          "counts": {
            "50": 0,
            "100": 0,
            "200": 2,
            "300": 143,
            "miss": 0,
            "max": 4695
          }
        },
        {
          "userId": "5156656",
          "score": 997735,
          "combo": 4840,
          "counts": {
            "50": 0,
            "100": 0,
            "200": 1,
            "300": 187,
            "miss": 0,
            "max": 4652
          }
        },
        {
          "userId": "10242062",
          "score": 997645,
          "combo": 4840,
          "counts": {
            "50": 0,
            "100": 0,
            "200": 2,
            "300": 173,
            "miss": 0,
            "max": 4665
          }
        },
        {
          "userId": "5156656",
          "score": 996439,
          "combo": 4840,
          "counts": {
            "50": 0,
            "100": 0,
            "200": 7,
            "300": 174,
            "miss": 0,
            "max": 4659
          }
        },
        {
          "userId": "10072733",
          "score": 995458,
          "combo": 4585,
          "counts": {
            "50": 0,
            "100": 0,
            "200": 0,
            "300": 119,
            "miss": 1,
            "max": 4720
          }
        },
        {
          "userId": "5243536",
          "score": 995250,
          "combo": 4840,
          "counts": {
            "50": 0,
            "100": 0,
            "200": 2,
            "300": 395,
            "miss": 0,
            "max": 4443
          }
        },
        {
          "userId": "3799946",
          "score": 994104,
          "combo": 4840,
          "counts": {
            "50": 1,
            "100": 0,
            "200": 6,
            "300": 358,
            "miss": 0,
            "max": 4475
          }
        },
        {
          "userId": "14245127",
          "score": 993755,
          "combo": 4840,
          "counts": {
            "50": 1,
            "100": 0,
            "200": 4,
            "300": 435,
            "miss": 0,
            "max": 4400
          }
        },
        {
          "userId": "7341471",
          "score": 993034,
          "combo": 4840,
          "counts": {
            "50": 0,
            "100": 0,
            "200": 5,
            "300": 534,
            "miss": 0,
            "max": 4301
          }
        },
        {
          "userId": "2288341",
          "score": 992748,
          "combo": 3339,
          "counts": {
            "50": 0,
            "100": 0,
            "200": 2,
            "300": 306,
            "miss": 1,
            "max": 4531
          }
        },
        {
          "userId": "12657177",
          "score": 992686,
          "combo": 3058,
          "counts": {
            "50": 0,
            "100": 0,
            "200": 0,
            "300": 356,
            "miss": 1,
            "max": 4483
          }
        },
        {
          "userId": "5243536",
          "score": 992403,
          "combo": 4545,
          "counts": {
            "50": 0,
            "100": 0,
            "200": 1,
            "300": 370,
            "miss": 1,
            "max": 4468
          }
        },
        {
          "userId": "4980256",
          "score": 990429,
          "combo": 4840,
          "counts": {
            "50": 0,
            "100": 2,
            "200": 7,
            "300": 645,
            "miss": 0,
            "max": 4186
          }
        },
        {
          "userId": "10015908",
          "score": 990256,
          "combo": 3910,
          "counts": {
            "50": 0,
            "100": 1,
            "200": 2,
            "300": 496,
            "miss": 1,
            "max": 4340
          }
        },
        {
          "userId": "9895650",
          "score": 988594,
          "combo": 2763,
          "counts": {
            "50": 0,
            "100": 0,
            "200": 1,
            "300": 427,
            "miss": 2,
            "max": 4410
          }
        },
        {
          "userId": "13382147",
          "score": 988586,
          "combo": 4717,
          "counts": {
            "50": 0,
            "100": 0,
            "200": 4,
            "300": 537,
            "miss": 4,
            "max": 4295
          }
        },
        {
          "userId": "11888159",
          "score": 987216,
          "combo": 4372,
          "counts": {
            "50": 2,
            "100": 3,
            "200": 8,
            "300": 356,
            "miss": 2,
            "max": 4469
          }
        },
        {
          "userId": "15806513",
          "score": 987056,
          "combo": 3970,
          "counts": {
            "50": 0,
            "100": 0,
            "200": 11,
            "300": 635,
            "miss": 1,
            "max": 4193
          }
        },
        {
          "userId": "13347579",
          "score": 979179,
          "combo": 3910,
          "counts": {
            "50": 0,
            "100": 2,
            "200": 11,
            "300": 580,
            "miss": 7,
            "max": 4240
          }
        }
      ],
      "pickCount": 10
    },
    {
      "category": "rice",
      "counts": {
        "bpm": -1,
        "sv": -1,
        "notes": {
          "total": 1763,
          "rice": 1741,
          "ln": 22,
          "single": -1,
          "jump": -1,
          "hand": -1,
          "quad": -1
        }
      },
      "title": "Skulk",
      "artist": "Echo !mage",
      "mapper": "Guilhermeziat",
      "difficulty": "[4K] Hidden",
      "beatmapId": "2943073",
      "beatmapSetId": "1429639",
      "hp": 8,
      "od": 9,
      "scores": [
        {
          "userId": "10083439",
          "score": 999530,
          "combo": 1785,
          "counts": {
            "50": 0,
            "100": 0,
            "200": 0,
            "300": 16,
            "miss": 0,
            "max": 1769
          }
        },
        {
          "userId": "5243536",
          "score": 998972,
          "combo": 1785,
          "counts": {
            "50": 0,
            "100": 0,
            "200": 0,
            "300": 35,
            "miss": 0,
            "max": 1750
          }
        },
        {
          "userId": "5243536",
          "score": 998679,
          "combo": 1785,
          "counts": {
            "50": 0,
            "100": 0,
            "200": 0,
            "300": 45,
            "miss": 0,
            "max": 1740
          }
        },
        {
          "userId": "2288341",
          "score": 998151,
          "combo": 1785,
          "counts": {
            "50": 0,
            "100": 0,
            "200": 0,
            "300": 63,
            "miss": 0,
            "max": 1722
          }
        },
        {
          "userId": "169992",
          "score": 997711,
          "combo": 1785,
          "counts": {
            "50": 0,
            "100": 0,
            "200": 0,
            "300": 78,
            "miss": 0,
            "max": 1707
          }
        },
        {
          "userId": "12028216",
          "score": 997272,
          "combo": 1785,
          "counts": {
            "50": 0,
            "100": 0,
            "200": 0,
            "300": 93,
            "miss": 0,
            "max": 1692
          }
        },
        {
          "userId": "10015908",
          "score": 996832,
          "combo": 1785,
          "counts": {
            "50": 0,
            "100": 0,
            "200": 0,
            "300": 108,
            "miss": 0,
            "max": 1677
          }
        },
        {
          "userId": "7341471",
          "score": 996803,
          "combo": 1785,
          "counts": {
            "50": 0,
            "100": 0,
            "200": 0,
            "300": 109,
            "miss": 0,
            "max": 1676
          }
        },
        {
          "userId": "10242062",
          "score": 996384,
          "combo": 1785,
          "counts": {
            "50": 0,
            "100": 0,
            "200": 4,
            "300": 34,
            "miss": 0,
            "max": 1747
          }
        },
        {
          "userId": "14245127",
          "score": 996004,
          "combo": 1785,
          "counts": {
            "50": 0,
            "100": 0,
            "200": 1,
            "300": 114,
            "miss": 0,
            "max": 1670
          }
        },
        {
          "userId": "10242062",
          "score": 995653,
          "combo": 1785,
          "counts": {
            "50": 0,
            "100": 0,
            "200": 4,
            "300": 59,
            "miss": 0,
            "max": 1722
          }
        },
        {
          "userId": "15806513",
          "score": 995156,
          "combo": 1785,
          "counts": {
            "50": 0,
            "100": 0,
            "200": 1,
            "300": 143,
            "miss": 0,
            "max": 1641
          }
        },
        {
          "userId": "12657177",
          "score": 995156,
          "combo": 1785,
          "counts": {
            "50": 0,
            "100": 1,
            "200": 2,
            "300": 77,
            "miss": 0,
            "max": 1705
          }
        },
        {
          "userId": "10015908",
          "score": 994368,
          "combo": 1785,
          "counts": {
            "50": 0,
            "100": 0,
            "200": 1,
            "300": 170,
            "miss": 0,
            "max": 1614
          }
        },
        {
          "userId": "4980256",
          "score": 992754,
          "combo": 1785,
          "counts": {
            "50": 0,
            "100": 0,
            "200": 2,
            "300": 203,
            "miss": 0,
            "max": 1580
          }
        },
        {
          "userId": "12297375",
          "score": 990031,
          "combo": 1785,
          "counts": {
            "50": 0,
            "100": 0,
            "200": 4,
            "300": 252,
            "miss": 0,
            "max": 1529
          }
        }
      ],
      "pickCount": 8
    },
    {
      "category": "rice",
      "counts": {
        "bpm": -1,
        "sv": -1,
        "notes": {
          "total": 2566,
          "rice": 2549,
          "ln": 17,
          "single": -1,
          "jump": -1,
          "hand": -1,
          "quad": -1
        }
      },
      "title": "DVP",
      "artist": "PUP",
      "mapper": "Chrubble",
      "difficulty": "[4K] still fucked up over you",
      "beatmapId": "1367763",
      "beatmapSetId": "645460",
      "hp": 8.5,
      "od": 7.5,
      "scores": [
        {
          "userId": "10083439",
          "score": 997202,
          "combo": 2583,
          "counts": {
            "50": 0,
            "100": 0,
            "200": 0,
            "300": 138,
            "miss": 0,
            "max": 2445
          }
        },
        {
          "userId": "5243536",
          "score": 996001,
          "combo": 2583,
          "counts": {
            "50": 0,
            "100": 0,
            "200": 1,
            "300": 176,
            "miss": 0,
            "max": 2406
          }
        },
        {
          "userId": "2288363",
          "score": 995585,
          "combo": 2583,
          "counts": {
            "50": 0,
            "100": 0,
            "200": 0,
            "300": 218,
            "miss": 0,
            "max": 2365
          }
        },
        {
          "userId": "5156656",
          "score": 994539,
          "combo": 2583,
          "counts": {
            "50": 0,
            "100": 0,
            "200": 3,
            "300": 203,
            "miss": 0,
            "max": 2377
          }
        },
        {
          "userId": "10242062",
          "score": 994532,
          "combo": 2583,
          "counts": {
            "50": 0,
            "100": 0,
            "200": 1,
            "300": 249,
            "miss": 0,
            "max": 2333
          }
        },
        {
          "userId": "2288341",
          "score": 994146,
          "combo": 2583,
          "counts": {
            "50": 0,
            "100": 0,
            "200": 1,
            "300": 267,
            "miss": 0,
            "max": 2315
          }
        },
        {
          "userId": "10242062",
          "score": 993939,
          "combo": 2583,
          "counts": {
            "50": 0,
            "100": 0,
            "200": 2,
            "300": 257,
            "miss": 0,
            "max": 2324
          }
        },
        {
          "userId": "11888159",
          "score": 992790,
          "combo": 2583,
          "counts": {
            "50": 0,
            "100": 0,
            "200": 2,
            "300": 312,
            "miss": 0,
            "max": 2269
          }
        },
        {
          "userId": "12657177",
          "score": 989798,
          "combo": 2583,
          "counts": {
            "50": 0,
            "100": 2,
            "200": 4,
            "300": 329,
            "miss": 0,
            "max": 2248
          }
        },
        {
          "userId": "3799946",
          "score": 989707,
          "combo": 2583,
          "counts": {
            "50": 0,
            "100": 0,
            "200": 6,
            "300": 377,
            "miss": 0,
            "max": 2200
          }
        },
        {
          "userId": "7341471",
          "score": 989042,
          "combo": 2583,
          "counts": {
            "50": 0,
            "100": 0,
            "200": 5,
            "300": 432,
            "miss": 0,
            "max": 2146
          }
        },
        {
          "userId": "13347579",
          "score": 987661,
          "combo": 2583,
          "counts": {
            "50": 0,
            "100": 0,
            "200": 9,
            "300": 414,
            "miss": 0,
            "max": 2160
          }
        },
        {
          "userId": "4980256",
          "score": 987042,
          "combo": 2583,
          "counts": {
            "50": 0,
            "100": 0,
            "200": 7,
            "300": 487,
            "miss": 0,
            "max": 2089
          }
        },
        {
          "userId": "7341471",
          "score": 986668,
          "combo": 2583,
          "counts": {
            "50": 0,
            "100": 1,
            "200": 2,
            "300": 574,
            "miss": 0,
            "max": 2006
          }
        },
        {
          "userId": "10879600",
          "score": 984850,
          "combo": 1780,
          "counts": {
            "50": 0,
            "100": 0,
            "200": 3,
            "300": 359,
            "miss": 1,
            "max": 2220
          }
        },
        {
          "userId": "11517895",
          "score": 967157,
          "combo": 1644,
          "counts": {
            "50": 0,
            "100": 2,
            "200": 7,
            "300": 486,
            "miss": 3,
            "max": 2085
          }
        }
      ],
      "pickCount": 8
    },
    {
      "category": "rice",
      "counts": {
        "bpm": -1,
        "sv": -1,
        "notes": {
          "total": 1670,
          "rice": 1662,
          "ln": 8,
          "single": -1,
          "jump": -1,
          "hand": -1,
          "quad": -1
        }
      },
      "title": "Recombination",
      "artist": "callasoiled",
      "mapper": "Elekton",
      "difficulty": "[4K] meiosis",
      "beatmapId": "1588236",
      "beatmapSetId": "754364",
      "hp": 8,
      "od": 8,
      "scores": [
        {
          "userId": "10242062",
          "score": 995034,
          "combo": 1678,
          "counts": {
            "50": 0,
            "100": 0,
            "200": 1,
            "300": 137,
            "miss": 0,
            "max": 1540
          }
        },
        {
          "userId": "5243536",
          "score": 993679,
          "combo": 1678,
          "counts": {
            "50": 0,
            "100": 0,
            "200": 0,
            "300": 203,
            "miss": 0,
            "max": 1475
          }
        },
        {
          "userId": "11888159",
          "score": 993265,
          "combo": 1678,
          "counts": {
            "50": 0,
            "100": 0,
            "200": 1,
            "300": 194,
            "miss": 0,
            "max": 1483
          }
        },
        {
          "userId": "11888159",
          "score": 991820,
          "combo": 1678,
          "counts": {
            "50": 0,
            "100": 0,
            "200": 3,
            "300": 196,
            "miss": 0,
            "max": 1479
          }
        },
        {
          "userId": "15806513",
          "score": 991768,
          "combo": 1678,
          "counts": {
            "50": 0,
            "100": 1,
            "200": 0,
            "300": 221,
            "miss": 0,
            "max": 1456
          }
        },
        {
          "userId": "12028216",
          "score": 990976,
          "combo": 1678,
          "counts": {
            "50": 0,
            "100": 1,
            "200": 2,
            "300": 202,
            "miss": 0,
            "max": 1473
          }
        },
        {
          "userId": "169992",
          "score": 990026,
          "combo": 1678,
          "counts": {
            "50": 0,
            "100": 0,
            "200": 6,
            "300": 187,
            "miss": 0,
            "max": 1485
          }
        },
        {
          "userId": "7341471",
          "score": 989615,
          "combo": 1678,
          "counts": {
            "50": 0,
            "100": 0,
            "200": 4,
            "300": 245,
            "miss": 0,
            "max": 1429
          }
        },
        {
          "userId": "5243536",
          "score": 983931,
          "combo": 870,
          "counts": {
            "50": 0,
            "100": 0,
            "200": 1,
            "300": 166,
            "miss": 1,
            "max": 1510
          }
        },
        {
          "userId": "12657177",
          "score": 982990,
          "combo": 1320,
          "counts": {
            "50": 0,
            "100": 0,
            "200": 1,
            "300": 198,
            "miss": 1,
            "max": 1478
          }
        },
        {
          "userId": "10242062",
          "score": 979988,
          "combo": 1411,
          "counts": {
            "50": 0,
            "100": 0,
            "200": 4,
            "300": 182,
            "miss": 2,
            "max": 1490
          }
        },
        {
          "userId": "13382147",
          "score": 925278,
          "combo": 465,
          "counts": {
            "50": 0,
            "100": 0,
            "200": 21,
            "300": 294,
            "miss": 7,
            "max": 1356
          }
        }
      ],
      "pickCount": 6
    },
    {
      "category": "rice",
      "counts": {
        "bpm": -1,
        "sv": -1,
        "notes": {
          "total": 1982,
          "rice": 1982,
          "ln": 0,
          "single": -1,
          "jump": -1,
          "hand": -1,
          "quad": -1
        }
      },
      "title": "Swamp Thing",
      "artist": "Pegboard Nerds",
      "mapper": "Shoegazer",
      "difficulty": "[4K] Swampgator 1.2x (162bpm)",
      "beatmapId": "2553540",
      "beatmapSetId": "1227404",
      "hp": 8.5,
      "od": 8,
      "scores": [
        {
          "userId": "10072733",
          "score": 998281,
          "combo": 1982,
          "counts": {
            "50": 0,
            "100": 0,
            "200": 0,
            "300": 65,
            "miss": 0,
            "max": 1917
          }
        },
        {
          "userId": "10083439",
          "score": 997358,
          "combo": 1982,
          "counts": {
            "50": 0,
            "100": 0,
            "200": 0,
            "300": 100,
            "miss": 0,
            "max": 1882
          }
        },
        {
          "userId": "10242062",
          "score": 996514,
          "combo": 1982,
          "counts": {
            "50": 0,
            "100": 0,
            "200": 0,
            "300": 132,
            "miss": 0,
            "max": 1850
          }
        },
        {
          "userId": "169992",
          "score": 996066,
          "combo": 1982,
          "counts": {
            "50": 0,
            "100": 0,
            "200": 0,
            "300": 149,
            "miss": 0,
            "max": 1833
          }
        },
        {
          "userId": "2288363",
          "score": 996013,
          "combo": 1982,
          "counts": {
            "50": 0,
            "100": 0,
            "200": 0,
            "300": 151,
            "miss": 0,
            "max": 1831
          }
        },
        {
          "userId": "5243536",
          "score": 995671,
          "combo": 1982,
          "counts": {
            "50": 0,
            "100": 0,
            "200": 0,
            "300": 164,
            "miss": 0,
            "max": 1818
          }
        },
        {
          "userId": "10879600",
          "score": 993796,
          "combo": 1982,
          "counts": {
            "50": 0,
            "100": 0,
            "200": 1,
            "300": 213,
            "miss": 0,
            "max": 1768
          }
        },
        {
          "userId": "5156656",
          "score": 993792,
          "combo": 1982,
          "counts": {
            "50": 1,
            "100": 0,
            "200": 1,
            "300": 159,
            "miss": 0,
            "max": 1821
          }
        },
        {
          "userId": "5243536",
          "score": 992390,
          "combo": 1982,
          "counts": {
            "50": 0,
            "100": 0,
            "200": 3,
            "300": 222,
            "miss": 0,
            "max": 1757
          }
        },
        {
          "userId": "2288341",
          "score": 992390,
          "combo": 1982,
          "counts": {
            "50": 0,
            "100": 1,
            "200": 1,
            "300": 223,
            "miss": 0,
            "max": 1757
          }
        },
        {
          "userId": "15806513",
          "score": 991776,
          "combo": 1982,
          "counts": {
            "50": 0,
            "100": 2,
            "200": 0,
            "300": 225,
            "miss": 0,
            "max": 1755
          }
        },
        {
          "userId": "12028216",
          "score": 990857,
          "combo": 1982,
          "counts": {
            "50": 0,
            "100": 1,
            "200": 3,
            "300": 237,
            "miss": 0,
            "max": 1741
          }
        },
        {
          "userId": "11888159",
          "score": 990599,
          "combo": 1982,
          "counts": {
            "50": 0,
            "100": 0,
            "200": 4,
            "300": 268,
            "miss": 0,
            "max": 1710
          }
        },
        {
          "userId": "7341471",
          "score": 988773,
          "combo": 1982,
          "counts": {
            "50": 0,
            "100": 0,
            "200": 4,
            "300": 338,
            "miss": 0,
            "max": 1640
          }
        },
        {
          "userId": "14245127",
          "score": 988517,
          "combo": 1982,
          "counts": {
            "50": 0,
            "100": 0,
            "200": 6,
            "300": 303,
            "miss": 0,
            "max": 1673
          }
        },
        {
          "userId": "13347579",
          "score": 987684,
          "combo": 1982,
          "counts": {
            "50": 0,
            "100": 0,
            "200": 6,
            "300": 335,
            "miss": 0,
            "max": 1641
          }
        },
        {
          "userId": "12297375",
          "score": 979198,
          "combo": 1982,
          "counts": {
            "50": 0,
            "100": 0,
            "200": 16,
            "300": 439,
            "miss": 0,
            "max": 1527
          }
        },
        {
          "userId": "10015908",
          "score": 971935,
          "combo": 952,
          "counts": {
            "50": 0,
            "100": 0,
            "200": 3,
            "300": 249,
            "miss": 3,
            "max": 1727
          }
        },
        {
          "userId": "11888159",
          "score": 971913,
          "combo": 996,
          "counts": {
            "50": 0,
            "100": 0,
            "200": 6,
            "300": 285,
            "miss": 2,
            "max": 1689
          }
        },
        {
          "userId": "10015908",
          "score": 969103,
          "combo": 886,
          "counts": {
            "50": 0,
            "100": 0,
            "200": 5,
            "300": 297,
            "miss": 3,
            "max": 1677
          }
        },
        {
          "userId": "13382147",
          "score": 964912,
          "combo": 883,
          "counts": {
            "50": 0,
            "100": 2,
            "200": 9,
            "300": 402,
            "miss": 2,
            "max": 1567
          }
        },
        {
          "userId": "9895650",
          "score": 769875,
          "combo": 483,
          "counts": {
            "50": 22,
            "100": 29,
            "200": 87,
            "300": 441,
            "miss": 41,
            "max": 1362
          }
        }
      ],
      "pickCount": 11
    },
    {
      "category": "ln",
      "counts": {
        "bpm": -1,
        "sv": -1,
        "notes": {
          "total": 1379,
          "rice": 293,
          "ln": 1086,
          "single": -1,
          "jump": -1,
          "hand": -1,
          "quad": -1
        }
      },
      "title": "Scars of FAUNA",
      "artist": "Nekomata Master",
      "mapper": "Raveille",
      "difficulty": "[4K] Orchid",
      "beatmapId": "1770185",
      "beatmapSetId": "846374",
      "hp": 7.6,
      "od": 7.6,
      "scores": [
        {
          "userId": "10072733",
          "score": 993501,
          "combo": 2465,
          "counts": {
            "50": 0,
            "100": 0,
            "200": 2,
            "300": 262,
            "miss": 0,
            "max": 2201
          }
        },
        {
          "userId": "13347579",
          "score": 991891,
          "combo": 2465,
          "counts": {
            "50": 0,
            "100": 0,
            "200": 0,
            "300": 383,
            "miss": 0,
            "max": 2082
          }
        },
        {
          "userId": "11517895",
          "score": 991744,
          "combo": 2465,
          "counts": {
            "50": 0,
            "100": 0,
            "200": 3,
            "300": 323,
            "miss": 0,
            "max": 2139
          }
        },
        {
          "userId": "10879600",
          "score": 991386,
          "combo": 2465,
          "counts": {
            "50": 0,
            "100": 0,
            "200": 3,
            "300": 340,
            "miss": 0,
            "max": 2122
          }
        },
        {
          "userId": "2288363",
          "score": 989068,
          "combo": 2465,
          "counts": {
            "50": 0,
            "100": 0,
            "200": 10,
            "300": 294,
            "miss": 0,
            "max": 2161
          }
        },
        {
          "userId": "13382147",
          "score": 988592,
          "combo": 2465,
          "counts": {
            "50": 0,
            "100": 0,
            "200": 9,
            "300": 339,
            "miss": 0,
            "max": 2117
          }
        },
        {
          "userId": "10015908",
          "score": 986845,
          "combo": 2465,
          "counts": {
            "50": 0,
            "100": 0,
            "200": 10,
            "300": 400,
            "miss": 0,
            "max": 2055
          }
        },
        {
          "userId": "10015908",
          "score": 985612,
          "combo": 2465,
          "counts": {
            "50": 0,
            "100": 0,
            "200": 12,
            "300": 415,
            "miss": 0,
            "max": 2038
          }
        },
        {
          "userId": "3799946",
          "score": 985583,
          "combo": 2465,
          "counts": {
            "50": 0,
            "100": 0,
            "200": 11,
            "300": 438,
            "miss": 0,
            "max": 2016
          }
        },
        {
          "userId": "12028216",
          "score": 984141,
          "combo": 2465,
          "counts": {
            "50": 0,
            "100": 0,
            "200": 15,
            "300": 418,
            "miss": 0,
            "max": 2032
          }
        },
        {
          "userId": "7341471",
          "score": 982179,
          "combo": 2465,
          "counts": {
            "50": 0,
            "100": 1,
            "200": 13,
            "300": 513,
            "miss": 0,
            "max": 1938
          }
        },
        {
          "userId": "15806513",
          "score": 981852,
          "combo": 2465,
          "counts": {
            "50": 0,
            "100": 0,
            "200": 17,
            "300": 483,
            "miss": 0,
            "max": 1965
          }
        },
        {
          "userId": "4980256",
          "score": 980309,
          "combo": 2465,
          "counts": {
            "50": 0,
            "100": 0,
            "200": 21,
            "300": 468,
            "miss": 0,
            "max": 1976
          }
        },
        {
          "userId": "11888159",
          "score": 979807,
          "combo": 1373,
          "counts": {
            "50": 0,
            "100": 1,
            "200": 7,
            "300": 360,
            "miss": 2,
            "max": 2095
          }
        },
        {
          "userId": "5156656",
          "score": 979305,
          "combo": 2465,
          "counts": {
            "50": 0,
            "100": 0,
            "200": 28,
            "300": 360,
            "miss": 0,
            "max": 2077
          }
        },
        {
          "userId": "14245127",
          "score": 976538,
          "combo": 1426,
          "counts": {
            "50": 0,
            "100": 0,
            "200": 15,
            "300": 454,
            "miss": 1,
            "max": 1995
          }
        },
        {
          "userId": "169992",
          "score": 976516,
          "combo": 1690,
          "counts": {
            "50": 1,
            "100": 1,
            "200": 18,
            "300": 351,
            "miss": 0,
            "max": 2094
          }
        },
        {
          "userId": "11888159",
          "score": 975844,
          "combo": 1301,
          "counts": {
            "50": 3,
            "100": 0,
            "200": 7,
            "300": 363,
            "miss": 3,
            "max": 2089
          }
        },
        {
          "userId": "7341471",
          "score": 974817,
          "combo": 2138,
          "counts": {
            "50": 0,
            "100": 0,
            "200": 14,
            "300": 412,
            "miss": 3,
            "max": 2036
          }
        },
        {
          "userId": "3799946",
          "score": 973469,
          "combo": 1865,
          "counts": {
            "50": 1,
            "100": 0,
            "200": 18,
            "300": 483,
            "miss": 1,
            "max": 1962
          }
        },
        {
          "userId": "12297375",
          "score": 971506,
          "combo": 1595,
          "counts": {
            "50": 1,
            "100": 0,
            "200": 23,
            "300": 533,
            "miss": 0,
            "max": 1908
          }
        },
        {
          "userId": "5156656",
          "score": 963736,
          "combo": 2348,
          "counts": {
            "50": 1,
            "100": 2,
            "200": 48,
            "300": 356,
            "miss": 0,
            "max": 2058
          }
        },
        {
          "userId": "5243536",
          "score": 959929,
          "combo": 1833,
          "counts": {
            "50": 1,
            "100": 1,
            "200": 34,
            "300": 552,
            "miss": 1,
            "max": 1876
          }
        },
        {
          "userId": "9895650",
          "score": 839389,
          "combo": 2282,
          "counts": {
            "50": 6,
            "100": 0,
            "200": 12,
            "300": 338,
            "miss": 111,
            "max": 1998
          }
        }
      ],
      "pickCount": 12
    },
    {
      "category": "ln",
      "counts": {
        "bpm": -1,
        "sv": -1,
        "notes": {
          "total": 2041,
          "rice": 451,
          "ln": 1590,
          "single": -1,
          "jump": -1,
          "hand": -1,
          "quad": -1
        }
      },
      "title": "#be_fortunate",
      "artist": "Hino Isuka",
      "mapper": "HowToPlayLN",
      "difficulty": "[4K] #be_nerfed",
      "beatmapId": "2349916",
      "beatmapSetId": "1099229",
      "hp": 0,
      "od": 8,
      "scores": [
        {
          "userId": "10072733",
          "score": 994401,
          "combo": 3631,
          "counts": {
            "50": 0,
            "100": 0,
            "200": 3,
            "300": 322,
            "miss": 0,
            "max": 3306
          }
        },
        {
          "userId": "10015908",
          "score": 991279,
          "combo": 3631,
          "counts": {
            "50": 0,
            "100": 0,
            "200": 3,
            "300": 540,
            "miss": 0,
            "max": 3088
          }
        },
        {
          "userId": "10015908",
          "score": 991179,
          "combo": 3631,
          "counts": {
            "50": 0,
            "100": 0,
            "200": 3,
            "300": 547,
            "miss": 0,
            "max": 3081
          }
        },
        {
          "userId": "3799946",
          "score": 989968,
          "combo": 3631,
          "counts": {
            "50": 0,
            "100": 0,
            "200": 9,
            "300": 498,
            "miss": 0,
            "max": 3124
          }
        },
        {
          "userId": "3799946",
          "score": 989578,
          "combo": 3631,
          "counts": {
            "50": 0,
            "100": 0,
            "200": 10,
            "300": 503,
            "miss": 0,
            "max": 3118
          }
        },
        {
          "userId": "13347579",
          "score": 989263,
          "combo": 3631,
          "counts": {
            "50": 0,
            "100": 0,
            "200": 7,
            "300": 592,
            "miss": 0,
            "max": 3032
          }
        },
        {
          "userId": "11517895",
          "score": 987732,
          "combo": 3631,
          "counts": {
            "50": 0,
            "100": 0,
            "200": 13,
            "300": 566,
            "miss": 0,
            "max": 3052
          }
        },
        {
          "userId": "12028216",
          "score": 987517,
          "combo": 3631,
          "counts": {
            "50": 0,
            "100": 0,
            "200": 13,
            "300": 581,
            "miss": 0,
            "max": 3037
          }
        },
        {
          "userId": "14245127",
          "score": 987356,
          "combo": 3631,
          "counts": {
            "50": 0,
            "100": 0,
            "200": 10,
            "300": 659,
            "miss": 0,
            "max": 2962
          }
        },
        {
          "userId": "5156656",
          "score": 984931,
          "combo": 3631,
          "counts": {
            "50": 0,
            "100": 0,
            "200": 22,
            "300": 562,
            "miss": 0,
            "max": 3047
          }
        },
        {
          "userId": "7341471",
          "score": 983004,
          "combo": 3631,
          "counts": {
            "50": 0,
            "100": 0,
            "200": 22,
            "300": 698,
            "miss": 0,
            "max": 2911
          }
        },
        {
          "userId": "5156656",
          "score": 979588,
          "combo": 3631,
          "counts": {
            "50": 0,
            "100": 0,
            "200": 39,
            "300": 561,
            "miss": 0,
            "max": 3031
          }
        },
        {
          "userId": "11888159",
          "score": 976976,
          "combo": 1849,
          "counts": {
            "50": 2,
            "100": 1,
            "200": 3,
            "300": 591,
            "miss": 8,
            "max": 3026
          }
        },
        {
          "userId": "169992",
          "score": 971943,
          "combo": 2542,
          "counts": {
            "50": 2,
            "100": 4,
            "200": 23,
            "300": 535,
            "miss": 6,
            "max": 3061
          }
        },
        {
          "userId": "12297375",
          "score": 966758,
          "combo": 3631,
          "counts": {
            "50": 0,
            "100": 0,
            "200": 69,
            "300": 809,
            "miss": 0,
            "max": 2753
          }
        },
        {
          "userId": "9895650",
          "score": 751704,
          "combo": 2432,
          "counts": {
            "50": 3,
            "100": 0,
            "200": 22,
            "300": 562,
            "miss": 257,
            "max": 2787
          }
        }
      ],
      "pickCount": 8
    },
    {
      "category": "ln",
      "counts": {
        "bpm": -1,
        "sv": -1,
        "notes": {
          "total": 1147,
          "rice": 298,
          "ln": 849,
          "single": -1,
          "jump": -1,
          "hand": -1,
          "quad": -1
        }
      },
      "title": "#Endroll",
      "artist": "uno & D.watt (IOSYS TRAX)",
      "mapper": "ByeForNow",
      "difficulty": "[4K] LN-VENLY",
      "beatmapId": "2156119",
      "beatmapSetId": "759313",
      "hp": 8,
      "od": 7,
      "scores": [
        {
          "userId": "2288363",
          "score": 994622,
          "combo": 1996,
          "counts": {
            "50": 0,
            "100": 0,
            "200": 1,
            "300": 183,
            "miss": 0,
            "max": 1812
          }
        },
        {
          "userId": "11888159",
          "score": 990502,
          "combo": 1996,
          "counts": {
            "50": 0,
            "100": 0,
            "200": 5,
            "300": 252,
            "miss": 0,
            "max": 1739
          }
        },
        {
          "userId": "10879600",
          "score": 990167,
          "combo": 1996,
          "counts": {
            "50": 0,
            "100": 0,
            "200": 5,
            "300": 265,
            "miss": 0,
            "max": 1726
          }
        },
        {
          "userId": "7341471",
          "score": 985969,
          "combo": 1996,
          "counts": {
            "50": 0,
            "100": 0,
            "200": 8,
            "300": 360,
            "miss": 0,
            "max": 1628
          }
        },
        {
          "userId": "13382147",
          "score": 984395,
          "combo": 1996,
          "counts": {
            "50": 0,
            "100": 1,
            "200": 12,
            "300": 288,
            "miss": 0,
            "max": 1695
          }
        },
        {
          "userId": "10015908",
          "score": 983323,
          "combo": 1020,
          "counts": {
            "50": 0,
            "100": 0,
            "200": 2,
            "300": 267,
            "miss": 1,
            "max": 1726
          }
        },
        {
          "userId": "12028216",
          "score": 982729,
          "combo": 1366,
          "counts": {
            "50": 0,
            "100": 0,
            "200": 2,
            "300": 290,
            "miss": 1,
            "max": 1703
          }
        },
        {
          "userId": "12297375",
          "score": 980927,
          "combo": 1996,
          "counts": {
            "50": 0,
            "100": 1,
            "200": 14,
            "300": 378,
            "miss": 0,
            "max": 1603
          }
        },
        {
          "userId": "11888159",
          "score": 978489,
          "combo": 1278,
          "counts": {
            "50": 1,
            "100": 1,
            "200": 10,
            "300": 245,
            "miss": 0,
            "max": 1739
          }
        },
        {
          "userId": "4980256",
          "score": 964749,
          "combo": 1595,
          "counts": {
            "50": 3,
            "100": 0,
            "200": 13,
            "300": 357,
            "miss": 3,
            "max": 1620
          }
        },
        {
          "userId": "7341471",
          "score": 962718,
          "combo": 1550,
          "counts": {
            "50": 0,
            "100": 0,
            "200": 16,
            "300": 353,
            "miss": 4,
            "max": 1623
          }
        },
        {
          "userId": "10242062",
          "score": 960727,
          "combo": 1746,
          "counts": {
            "50": 2,
            "100": 1,
            "200": 28,
            "300": 503,
            "miss": 0,
            "max": 1462
          }
        },
        {
          "userId": "12657177",
          "score": 955374,
          "combo": 1770,
          "counts": {
            "50": 0,
            "100": 1,
            "200": 24,
            "300": 436,
            "miss": 6,
            "max": 1529
          }
        },
        {
          "userId": "169992",
          "score": 950590,
          "combo": 1016,
          "counts": {
            "50": 4,
            "100": 0,
            "200": 19,
            "300": 321,
            "miss": 4,
            "max": 1648
          }
        }
      ],
      "pickCount": 7
    },
    {
      "category": "ln",
      "counts": {
        "bpm": -1,
        "sv": -1,
        "notes": {
          "total": 1522,
          "rice": 4,
          "ln": 1518,
          "single": -1,
          "jump": -1,
          "hand": -1,
          "quad": -1
        }
      },
      "title": "Catanoph",
      "artist": "An",
      "mapper": "Toaph Daddy",
      "difficulty": "[4K] Eternity (cut)",
      "beatmapId": "2939618",
      "beatmapSetId": "696257",
      "hp": 6,
      "od": 7,
      "scores": [
        {
          "userId": "10879600",
          "score": 992638,
          "combo": 3040,
          "counts": {
            "50": 0,
            "100": 0,
            "200": 2,
            "300": 384,
            "miss": 0,
            "max": 2654
          }
        },
        {
          "userId": "2288363",
          "score": 990782,
          "combo": 3040,
          "counts": {
            "50": 0,
            "100": 0,
            "200": 4,
            "300": 448,
            "miss": 0,
            "max": 2588
          }
        },
        {
          "userId": "10015908",
          "score": 988825,
          "combo": 3040,
          "counts": {
            "50": 0,
            "100": 0,
            "200": 7,
            "300": 496,
            "miss": 0,
            "max": 2537
          }
        },
        {
          "userId": "13382147",
          "score": 988451,
          "combo": 3040,
          "counts": {
            "50": 0,
            "100": 0,
            "200": 13,
            "300": 384,
            "miss": 0,
            "max": 2643
          }
        },
        {
          "userId": "10015908",
          "score": 988377,
          "combo": 3040,
          "counts": {
            "50": 0,
            "100": 0,
            "200": 8,
            "300": 500,
            "miss": 0,
            "max": 2532
          }
        },
        {
          "userId": "3799946",
          "score": 986445,
          "combo": 3040,
          "counts": {
            "50": 0,
            "100": 0,
            "200": 14,
            "300": 480,
            "miss": 0,
            "max": 2546
          }
        },
        {
          "userId": "14245127",
          "score": 983477,
          "combo": 3040,
          "counts": {
            "50": 0,
            "100": 0,
            "200": 18,
            "300": 566,
            "miss": 0,
            "max": 2456
          }
        },
        {
          "userId": "3799946",
          "score": 982545,
          "combo": 3040,
          "counts": {
            "50": 0,
            "100": 0,
            "200": 22,
            "300": 532,
            "miss": 0,
            "max": 2486
          }
        },
        {
          "userId": "11517895",
          "score": 979928,
          "combo": 2205,
          "counts": {
            "50": 1,
            "100": 0,
            "200": 6,
            "300": 433,
            "miss": 4,
            "max": 2596
          }
        },
        {
          "userId": "12297375",
          "score": 978089,
          "combo": 3040,
          "counts": {
            "50": 0,
            "100": 1,
            "200": 24,
            "300": 708,
            "miss": 0,
            "max": 2307
          }
        },
        {
          "userId": "5156656",
          "score": 976609,
          "combo": 3029,
          "counts": {
            "50": 1,
            "100": 4,
            "200": 26,
            "300": 537,
            "miss": 0,
            "max": 2472
          }
        },
        {
          "userId": "11888159",
          "score": 973482,
          "combo": 1329,
          "counts": {
            "50": 3,
            "100": 1,
            "200": 6,
            "300": 452,
            "miss": 1,
            "max": 2577
          }
        }
      ],
      "pickCount": 6
    },
    {
      "category": "hybrid",
      "counts": {
        "bpm": -1,
        "sv": -1,
        "notes": {
          "total": 2276,
          "rice": 1969,
          "ln": 307,
          "single": -1,
          "jump": -1,
          "hand": -1,
          "quad": -1
        }
      },
      "title": "PARADOXX",
      "artist": "SLAM & NATO",
      "mapper": "lemonguy",
      "difficulty": "[4K] Challenge",
      "beatmapId": "2432909",
      "beatmapSetId": "1166344",
      "hp": 9,
      "od": 8,
      "scores": [
        {
          "userId": "10072733",
          "score": 997346,
          "combo": 2583,
          "counts": {
            "50": 0,
            "100": 0,
            "200": 1,
            "300": 109,
            "miss": 0,
            "max": 2473
          }
        },
        {
          "userId": "10083439",
          "score": 996178,
          "combo": 2583,
          "counts": {
            "50": 0,
            "100": 0,
            "200": 2,
            "300": 144,
            "miss": 0,
            "max": 2437
          }
        },
        {
          "userId": "2288363",
          "score": 995706,
          "combo": 2583,
          "counts": {
            "50": 0,
            "100": 0,
            "200": 0,
            "300": 212,
            "miss": 0,
            "max": 2371
          }
        },
        {
          "userId": "10879600",
          "score": 993743,
          "combo": 2583,
          "counts": {
            "50": 0,
            "100": 0,
            "200": 1,
            "300": 287,
            "miss": 0,
            "max": 2295
          }
        },
        {
          "userId": "5156656",
          "score": 993200,
          "combo": 2583,
          "counts": {
            "50": 1,
            "100": 0,
            "200": 3,
            "300": 215,
            "miss": 0,
            "max": 2364
          }
        },
        {
          "userId": "9895650",
          "score": 992763,
          "combo": 2583,
          "counts": {
            "50": 0,
            "100": 0,
            "200": 3,
            "300": 291,
            "miss": 0,
            "max": 2289
          }
        },
        {
          "userId": "10242062",
          "score": 990788,
          "combo": 2583,
          "counts": {
            "50": 0,
            "100": 0,
            "200": 10,
            "300": 233,
            "miss": 0,
            "max": 2340
          }
        },
        {
          "userId": "7341471",
          "score": 988454,
          "combo": 2583,
          "counts": {
            "50": 0,
            "100": 0,
            "200": 2,
            "300": 528,
            "miss": 0,
            "max": 2053
          }
        },
        {
          "userId": "3799946",
          "score": 988321,
          "combo": 2583,
          "counts": {
            "50": 1,
            "100": 0,
            "200": 3,
            "300": 458,
            "miss": 0,
            "max": 2121
          }
        },
        {
          "userId": "2288341",
          "score": 987668,
          "combo": 2016,
          "counts": {
            "50": 0,
            "100": 0,
            "200": 2,
            "300": 241,
            "miss": 1,
            "max": 2339
          }
        },
        {
          "userId": "10242062",
          "score": 985147,
          "combo": 2583,
          "counts": {
            "50": 1,
            "100": 2,
            "200": 14,
            "300": 284,
            "miss": 0,
            "max": 2282
          }
        },
        {
          "userId": "5156656",
          "score": 984858,
          "combo": 2067,
          "counts": {
            "50": 1,
            "100": 0,
            "200": 7,
            "300": 218,
            "miss": 1,
            "max": 2356
          }
        },
        {
          "userId": "13347579",
          "score": 981031,
          "combo": 1554,
          "counts": {
            "50": 0,
            "100": 0,
            "200": 10,
            "300": 394,
            "miss": 1,
            "max": 2178
          }
        },
        {
          "userId": "5243536",
          "score": 979911,
          "combo": 1311,
          "counts": {
            "50": 1,
            "100": 1,
            "200": 3,
            "300": 288,
            "miss": 2,
            "max": 2288
          }
        },
        {
          "userId": "4980256",
          "score": 974168,
          "combo": 1623,
          "counts": {
            "50": 2,
            "100": 0,
            "200": 12,
            "300": 357,
            "miss": 2,
            "max": 2210
          }
        },
        {
          "userId": "12657177",
          "score": 965525,
          "combo": 1211,
          "counts": {
            "50": 3,
            "100": 3,
            "200": 14,
            "300": 347,
            "miss": 3,
            "max": 2213
          }
        }
      ],
      "pickCount": 8
    },
    {
      "category": "hybrid",
      "counts": {
        "bpm": -1,
        "sv": -1,
        "notes": {
          "total": 1807,
          "rice": 1300,
          "ln": 507,
          "single": -1,
          "jump": -1,
          "hand": -1,
          "quad": -1
        }
      },
      "title": "Carry Me Away",
      "artist": "lapix",
      "mapper": "arpia97",
      "difficulty": "[4K] Daybreak",
      "beatmapId": "1793444",
      "beatmapSetId": "858142",
      "hp": 8.5,
      "od": 7.5,
      "scores": [
        {
          "userId": "2288363",
          "score": 994128,
          "combo": 2314,
          "counts": {
            "50": 0,
            "100": 0,
            "200": 3,
            "300": 193,
            "miss": 0,
            "max": 2118
          }
        },
        {
          "userId": "10879600",
          "score": 993715,
          "combo": 2314,
          "counts": {
            "50": 0,
            "100": 0,
            "200": 1,
            "300": 256,
            "miss": 0,
            "max": 2057
          }
        },
        {
          "userId": "5156656",
          "score": 993649,
          "combo": 2314,
          "counts": {
            "50": 0,
            "100": 0,
            "200": 4,
            "300": 192,
            "miss": 0,
            "max": 2118
          }
        },
        {
          "userId": "10242062",
          "score": 993049,
          "combo": 2314,
          "counts": {
            "50": 0,
            "100": 0,
            "200": 3,
            "300": 241,
            "miss": 0,
            "max": 2070
          }
        },
        {
          "userId": "15806513",
          "score": 992883,
          "combo": 2314,
          "counts": {
            "50": 0,
            "100": 0,
            "200": 1,
            "300": 293,
            "miss": 0,
            "max": 2020
          }
        },
        {
          "userId": "3799946",
          "score": 992854,
          "combo": 2314,
          "counts": {
            "50": 0,
            "100": 0,
            "200": 2,
            "300": 272,
            "miss": 0,
            "max": 2040
          }
        },
        {
          "userId": "169992",
          "score": 992442,
          "combo": 2314,
          "counts": {
            "50": 0,
            "100": 0,
            "200": 3,
            "300": 268,
            "miss": 0,
            "max": 2043
          }
        },
        {
          "userId": "14245127",
          "score": 992165,
          "combo": 2314,
          "counts": {
            "50": 0,
            "100": 0,
            "200": 5,
            "300": 236,
            "miss": 0,
            "max": 2073
          }
        },
        {
          "userId": "11888159",
          "score": 992158,
          "combo": 2314,
          "counts": {
            "50": 0,
            "100": 1,
            "200": 3,
            "300": 237,
            "miss": 0,
            "max": 2073
          }
        },
        {
          "userId": "11888159",
          "score": 991283,
          "combo": 2314,
          "counts": {
            "50": 0,
            "100": 0,
            "200": 5,
            "300": 275,
            "miss": 0,
            "max": 2034
          }
        },
        {
          "userId": "12028216",
          "score": 990859,
          "combo": 2314,
          "counts": {
            "50": 1,
            "100": 0,
            "200": 5,
            "300": 240,
            "miss": 0,
            "max": 2068
          }
        },
        {
          "userId": "5243536",
          "score": 989264,
          "combo": 2314,
          "counts": {
            "50": 0,
            "100": 1,
            "200": 7,
            "300": 277,
            "miss": 0,
            "max": 2029
          }
        },
        {
          "userId": "5243536",
          "score": 989208,
          "combo": 2314,
          "counts": {
            "50": 0,
            "100": 0,
            "200": 7,
            "300": 323,
            "miss": 0,
            "max": 1984
          }
        },
        {
          "userId": "13347579",
          "score": 988925,
          "combo": 2314,
          "counts": {
            "50": 0,
            "100": 3,
            "200": 4,
            "300": 272,
            "miss": 0,
            "max": 2035
          }
        },
        {
          "userId": "7341471",
          "score": 988753,
          "combo": 2314,
          "counts": {
            "50": 0,
            "100": 0,
            "200": 3,
            "300": 433,
            "miss": 0,
            "max": 1878
          }
        },
        {
          "userId": "5156656",
          "score": 984618,
          "combo": 1384,
          "counts": {
            "50": 0,
            "100": 0,
            "200": 6,
            "300": 226,
            "miss": 1,
            "max": 2081
          }
        },
        {
          "userId": "10015908",
          "score": 984316,
          "combo": 1852,
          "counts": {
            "50": 0,
            "100": 0,
            "200": 4,
            "300": 282,
            "miss": 1,
            "max": 2027
          }
        },
        {
          "userId": "7341471",
          "score": 983537,
          "combo": 1512,
          "counts": {
            "50": 0,
            "100": 0,
            "200": 4,
            "300": 317,
            "miss": 1,
            "max": 1992
          }
        },
        {
          "userId": "4980256",
          "score": 981644,
          "combo": 1206,
          "counts": {
            "50": 1,
            "100": 0,
            "200": 5,
            "300": 327,
            "miss": 1,
            "max": 1980
          }
        },
        {
          "userId": "13382147",
          "score": 976936,
          "combo": 1149,
          "counts": {
            "50": 1,
            "100": 1,
            "200": 2,
            "300": 298,
            "miss": 1,
            "max": 2011
          }
        }
      ],
      "pickCount": 10
    },
    {
      "category": "hybrid",
      "counts": {
        "bpm": -1,
        "sv": -1,
        "notes": {
          "total": 2919,
          "rice": 2125,
          "ln": 794,
          "single": -1,
          "jump": -1,
          "hand": -1,
          "quad": -1
        }
      },
      "title": "Ushinaharerurunazuki",
      "artist": "Marmalade butcher",
      "mapper": "Suu is my waifu",
      "difficulty": "[4K] Uteruchesis",
      "beatmapId": "2495433",
      "beatmapSetId": "1023160",
      "hp": 8,
      "od": 8.3,
      "scores": [
        {
          "userId": "2288363",
          "score": 994286,
          "combo": 3713,
          "counts": {
            "50": 0,
            "100": 0,
            "200": 3,
            "300": 339,
            "miss": 0,
            "max": 3371
          }
        },
        {
          "userId": "12028216",
          "score": 990396,
          "combo": 3713,
          "counts": {
            "50": 0,
            "100": 0,
            "200": 6,
            "300": 550,
            "miss": 0,
            "max": 3157
          }
        },
        {
          "userId": "3799946",
          "score": 990121,
          "combo": 3713,
          "counts": {
            "50": 0,
            "100": 0,
            "200": 5,
            "300": 592,
            "miss": 0,
            "max": 3116
          }
        },
        {
          "userId": "5156656",
          "score": 989562,
          "combo": 3713,
          "counts": {
            "50": 0,
            "100": 0,
            "200": 15,
            "300": 409,
            "miss": 0,
            "max": 3289
          }
        },
        {
          "userId": "4980256",
          "score": 988613,
          "combo": 3713,
          "counts": {
            "50": 0,
            "100": 0,
            "200": 12,
            "300": 544,
            "miss": 0,
            "max": 3157
          }
        },
        {
          "userId": "10879600",
          "score": 986659,
          "combo": 3159,
          "counts": {
            "50": 0,
            "100": 1,
            "200": 3,
            "300": 445,
            "miss": 2,
            "max": 3262
          }
        },
        {
          "userId": "5156656",
          "score": 985655,
          "combo": 1961,
          "counts": {
            "50": 1,
            "100": 0,
            "200": 12,
            "300": 380,
            "miss": 1,
            "max": 3319
          }
        },
        {
          "userId": "13347579",
          "score": 985178,
          "combo": 1926,
          "counts": {
            "50": 0,
            "100": 0,
            "200": 7,
            "300": 578,
            "miss": 1,
            "max": 3127
          }
        },
        {
          "userId": "7341471",
          "score": 984735,
          "combo": 3713,
          "counts": {
            "50": 0,
            "100": 0,
            "200": 9,
            "300": 890,
            "miss": 0,
            "max": 2814
          }
        },
        {
          "userId": "14245127",
          "score": 984231,
          "combo": 3713,
          "counts": {
            "50": 0,
            "100": 2,
            "200": 19,
            "300": 618,
            "miss": 0,
            "max": 3074
          }
        },
        {
          "userId": "11517895",
          "score": 983610,
          "combo": 3713,
          "counts": {
            "50": 0,
            "100": 3,
            "200": 13,
            "300": 751,
            "miss": 0,
            "max": 2946
          }
        },
        {
          "userId": "3799946",
          "score": 981716,
          "combo": 3579,
          "counts": {
            "50": 1,
            "100": 1,
            "200": 11,
            "300": 590,
            "miss": 3,
            "max": 3107
          }
        },
        {
          "userId": "169992",
          "score": 981240,
          "combo": 1786,
          "counts": {
            "50": 0,
            "100": 0,
            "200": 10,
            "300": 471,
            "miss": 2,
            "max": 3230
          }
        },
        {
          "userId": "10015908",
          "score": 979953,
          "combo": 1747,
          "counts": {
            "50": 0,
            "100": 1,
            "200": 5,
            "300": 555,
            "miss": 3,
            "max": 3149
          }
        }
      ],
      "pickCount": 7
    },
    {
      "category": "tb",
      "counts": {
        "bpm": -1,
        "sv": -1,
        "notes": {
          "total": -1,
          "rice": -1,
          "ln": -1,
          "single": -1,
          "jump": -1,
          "hand": -1,
          "quad": -1
        }
      },
      "title": "Arche",
      "artist": "Camellia",
      "mapper": "-mint-",
      "difficulty": "Camellia",
      "beatmapId": "2942932",
      "beatmapSetId": "1429563",
      "hp": "?",
      "od": "?",
      "scores": [
        {
          "userId": "12028216",
          "score": 972319,
          "combo": 4137,
          "counts": {
            "50": 0,
            "100": 2,
            "200": 52,
            "300": 955,
            "miss": 4,
            "max": 4560
          }
        },
        {
          "userId": "169992",
          "score": 967213,
          "combo": 1826,
          "counts": {
            "50": 4,
            "100": 3,
            "200": 51,
            "300": 855,
            "miss": 6,
            "max": 4654
          }
        }
      ],
      "pickCount": 1
    }
  ]
}
